pip_faster.py
venv_update.py
venv_update-4.0.0.dist-info/LICENSE
venv_update-4.0.0.dist-info/METADATA
venv_update-4.0.0.dist-info/WHEEL
venv_update-4.0.0.dist-info/entry_points.txt
venv_update-4.0.0.dist-info/top_level.txt
venv_update-4.0.0.dist-info/RECORD
